[
    {
        "name": "NexT",
        "link": "https://github.com/theme-next/hexo-theme-next",
        "description": "NexT is an elegant and powerful theme",
        "watch": 80,
        "star": 3672,
        "fork": 1146
    },
    {
        "name": "indigo",
        "link": "https://github.com/yscoder/hexo-theme-indigo",
        "description": "Material Design theme",
        "watch": 70,
        "star": 2305,
        "fork": 491
    },
    {
        "name": "Apollo",
        "link": "https://github.com/pinggod/hexo-theme-apollo",
        "description": "A theme inspired by http://cn.vuejs.org/",
        "watch": 45,
        "star": 1671,
        "fork": 504
    },
    {
        "name": "Yelee",
        "link": "https://github.com/MOxFIVE/hexo-theme-yelee",
        "description": "Another simple and elegant theme by MOxFIVE",
        "watch": 66,
        "star": 1314,
        "fork": 2183
    },
    {
        "name": "Cactus",
        "link": "https://github.com/probberechts/hexo-theme-cactus",
        "description": "A responsive, clean and simple theme for a personal webpage",
        "watch": 35,
        "star": 1254,
        "fork": 384
    },
    {
        "name": "Even",
        "link": "https://github.com/ahonn/hexo-theme-even",
        "description": "A simple theme",
        "watch": 27,
        "star": 1069,
        "fork": 196
    },
    {
        "name": "Archer",
        "link": "https://github.com/fi3ework/hexo-theme-archer",
        "description": "A smart and modern theme",
        "watch": 21,
        "star": 822,
        "fork": 182
    },
    {
        "name": "Asnippet",
        "link": "https://github.com/shenliyang/hexo-theme-snippet",
        "description": "A simple and interesting theme",
        "watch": 20,
        "star": 809,
        "fork": 179
    },
    {
        "name": "Anisina",
        "link": "https://github.com/haojen/hexo-theme-Anisina",
        "description": "A support qiniu image cdn , simple responsive theme",
        "watch": 25,
        "star": 709,
        "fork": 157
    },
    {
        "name": "Diaspora",
        "link": "https://github.com/Fechin/hexo-theme-diaspora",
        "description": "A clean and responsive theme",
        "watch": 4,
        "star": 505,
        "fork": 140
    }
]